{"examples_cgnet_egg.md":"BcoO663f","examples_co2_brine_2d_vertical.md":"CrEnbo2O","examples_co2_props.md":"D1jiEmPt","examples_co2_sloped.md":"D5hETHLv","examples_compositional_5components.md":"BEwN5W6t","examples_data_input_file.md":"Brml6j8A","examples_five_spot_ensemble.md":"C6e8NlZ_","examples_intro_sensitivities.md":"BfB2wJAh","examples_model_coarsening.md":"Ck2n4hnU","examples_optimize_simple_bl.md":"CMF0Skzh","examples_relperms.md":"B3n9XMwI","examples_two_phase_buckley_leverett.md":"DumlMjYk","examples_two_phase_gravity_segregation.md":"CgwT10l1","examples_two_phase_unstable_gravity.md":"B9M3ryHJ","examples_validation_compositional.md":"BkN-AL70","examples_validation_egg.md":"W4cgt-f0","examples_validation_mrst.md":"DCvMERLH","examples_validation_norne_nohyst.md":"COWCqpGb","examples_validation_olympus_1.md":"DGsCiFF7","examples_validation_spe1.md":"duyzMs-3","examples_validation_spe9.md":"kjXiSizZ","examples_wells_intro.md":"Cf1mcckR","extras_faq.md":"BbUs0fhC","extras_refs.md":"DxdzT3Uq","index.md":"BruUOAGp","man_advanced_compiled.md":"DVFU_LUG","man_advanced_mpi.md":"yPUXviB_","man_basics_forces.md":"CjilJoLy","man_basics_input_files.md":"C3pFUJ1T","man_basics_models.md":"D7BjcJI7","man_basics_parameters.md":"DpwhQRe6","man_basics_plotting.md":"tgGlk46y","man_basics_primary.md":"BqeEqFfa","man_basics_secondary.md":"BUKQMofo","man_basics_solution.md":"9kYPpZot","man_basics_systems.md":"DfT5GC0U","man_basics_utilities.md":"l5vbkgjC","man_basics_wells.md":"i-cuiOD5","man_first_ex.md":"eP-XfmHA","man_highlevel.md":"DG3_s8qg","man_intro.md":"DpNSR7pK","notebooks_empty.md":"DreYaJX1","ref_jutul.md":"BfWHw0Yo"}
